{
    "abject": "miserable",
    "acerb": "bitter",
    "acerbic": "bitter",
    "acid": "bitter",
    "acrid": "bitter",
    "acrimonious": "bitter",
    "active": "active",
    "active_agent": "active",
    "active_voice": "active",
    "admonish": "discouraged",
    "aflutter": "nervous",
    "alert": "lively",
    "alive": "active",
    "amaze": "bewildered",
    "angered": "furious",
    "angry": "Angry",
    "annoy": "annoyed",
    "annoyed": "annoyed",
    "anxious": "uneasy",
    "arouse": "energized",
    "at_sea": "confused",
    "aweary": "weary",
    "awkward": "uneasy",
    "bad-tempered": "grumpy",
    "baffle": "bewildered",
    "baffled": "confused",
    "beat": "exhausted",
    "bedevil": "confused",
    "befuddle": "confused",
    "befuddled": "confused",
    "bemuse": "bewildered",
    "bemused": "confused",
    "bewilder": "bewildered",
    "bewildered": "confused",
    "biting": "bitter",
    "bitingly": "bitter",
    "bitter": "bitter",
    "bitterly": "bitter",
    "bitterness": "bitter",
    "blistering": "bitter",
    "blur": "confused",
    "bother": "annoyed",
    "bouncy": "lively",
    "brace": "energized",
    "brisk": "lively",
    "broken": "confused",
    "cark": "distracted",
    "caustic": "bitter",
    "chafe": "annoyed",
    "changeable": "uncertain",
    "combat-ready": "active",
    "confound": "confused",
    "confounded": "confused",
    "confuse": "confused",
    "confused": "confused",
    "consume": "exhausted",
    "crabbed": "grumpy",
    "crabby": "grumpy",
    "cross": "grumpy",
    "dead": "drained",
    "debilitate": "drained",
    "deflect": "distracted",
    "demoralised": "discouraged",
    "demoralized": "discouraged",
    "deplete": "exhausted",
    "deplorable": "sad",
    "despicable": "worthless",
    "deter": "discouraged",
    "devil": "annoyed",
    "discharge": "exhausted",
    "discombobulate": "confused",
    "disconcert": "confused",
    "disconnected": "confused",
    "discourage": "discouraged",
    "discouraged": "discouraged",
    "disheartened": "discouraged",
    "disjointed": "confused",
    "disorder": "distracted",
    "disordered": "confused",
    "disoriented": "confused",
    "disquiet": "distracted",
    "distract": "distracted",
    "distracted": "distracted",
    "distrait": "distracted",
    "distressed": "unhappy",
    "distressing": "sad",
    "dog-tired": "worn-out",
    "drain": "drained",
    "drained": "drained",
    "dumbfound": "bewildered",
    "dying": "anxious",
    "dynamic": "active",
    "dysphoric": "unhappy",
    "eat": "exhausted",
    "eat_up": "exhausted",
    "eject": "exhausted",
    "energetic": "energetic",
    "energise": "energized",
    "energize": "energized",
    "enfeeble": "drained",
    "enraged": "furious",
    "excite": "energized",
    "execrable": "miserable",
    "exhaust": "exhausted",
    "exhausted": "worn-out",
    "expel": "exhausted",
    "fag": "fatigued",
    "fag_out": "fatigued",
    "fagged": "worn-out",
    "fatigue": "fatigued",
    "fatigued": "worn-out",
    "ferocious": "furious",
    "fierce": "furious",
    "fighting": "active",
    "flighty": "nervous",
    "flummox": "bewildered",
    "flurry": "confused",
    "forgetful": "forgetful",
    "fox": "confused",
    "fuddle": "confused",
    "full_of_life": "lively",
    "furious": "Angry",
    "fussy": "grumpy",
    "garbled": "confused",
    "get": "bewildered",
    "get_at": "annoyed",
    "get_to": "annoyed",
    "gravel": "annoyed",
    "grouchy": "grumpy",
    "grumpy": "grumpy",
    "gumptious": "energetic",
    "hapless": "miserable",
    "harassed": "annoyed",
    "harried": "annoyed",
    "helpless": "helpless",
    "hopeless": "hopeless",
    "ill-tempered": "grumpy",
    "ill_at_ease": "uneasy",
    "illogical": "confused",
    "incapacitated": "helpless",
    "incertain": "uncertain",
    "industrious": "energetic",
    "infelicitous": "unhappy",
    "infuriated": "furious",
    "irritate": "annoyed",
    "irritated": "annoyed",
    "jade": "fatigued",
    "jumble": "confused",
    "knackered": "drained",
    "lamentable": "sad",
    "live": "lively",
    "lively": "lively",
    "lost": "confused",
    "low": "miserable",
    "low-down": "miserable",
    "maddened": "furious",
    "mazed": "confused",
    "measly": "miserable",
    "merry": "lively",
    "miffed": "annoyed",
    "mindless": "forgetful",
    "miserable": "miserable",
    "misfortunate": "miserable",
    "mix_up": "confused",
    "mixed-up": "confused",
    "monish": "discouraged",
    "mystify": "bewildered",
    "nark": "annoyed",
    "nervous": "uneasy",
    "nettle": "annoyed",
    "nettled": "annoyed",
    "neural": "nervous",
    "nonplus": "bewildered",
    "oblivious": "forgetful",
    "obnubilate": "confused",
    "obscure": "confused",
    "outwear": "fatigued",
    "pall": "fatigued",
    "paltry": "miserable",
    "participating": "active",
    "pathetic": "miserable",
    "peeved": "annoyed",
    "perk_up": "energized",
    "perplex": "bewildered",
    "perturb": "distracted",
    "pestered": "annoyed",
    "piercingly": "bitter",
    "pissed": "annoyed",
    "pissed_off": "annoyed",
    "piteous": "miserable",
    "pitiable": "miserable",
    "pitiful": "sad",
    "play_out": "exhausted",
    "played_out": "worn-out",
    "poor": "miserable",
    "pose": "bewildered",
    "put_off": "confused",
    "puzzle": "bewildered",
    "queasy": "uneasy",
    "racy": "lively",
    "raddled": "worn-out",
    "rag": "annoyed",
    "raging": "Angry",
    "rattling": "lively",
    "release": "exhausted",
    "resentful": "resentful",
    "resilient": "lively",
    "restless": "uneasy",
    "rile": "annoyed",
    "riled": "annoyed",
    "roiled": "annoyed",
    "run_down": "exhausted",
    "run_out": "drained",
    "run_through": "exhausted",
    "sad": "sad",
    "sap": "exhausted",
    "savage": "furious",
    "scattered": "confused",
    "scummy": "miserable",
    "scurvy": "miserable",
    "short": "forgetful",
    "skittish": "nervous",
    "slimy": "worthless",
    "snappy": "lively",
    "sorry": "sad",
    "spanking": "lively",
    "spent": "worn-out",
    "spooky": "nervous",
    "springy": "lively",
    "steamed": "annoyed",
    "stick": "bewildered",
    "stimulate": "energized",
    "strain": "tense",
    "stung": "annoyed",
    "stupefy": "bewildered",
    "suffering": "miserable",
    "sulfurous": "bitter",
    "sulphurous": "bitter",
    "tempestuous": "Angry",
    "tense": "tense",
    "tense_up": "tense",
    "throw": "confused",
    "tire": "fatigued",
    "tire_out": "fatigued",
    "trouble": "distracted",
    "tucker": "exhausted",
    "tucker_out": "exhausted",
    "ugly": "worthless",
    "uncertain": "uncertain",
    "unconnected": "confused",
    "uneasy": "uneasy",
    "ungratified": "restless",
    "unhappy": "unhappy",
    "unhinge": "distracted",
    "unmindful": "forgetful",
    "unquiet": "uneasy",
    "unretentive": "forgetful",
    "unsatisfied": "restless",
    "unsealed": "uncertain",
    "unsettled": "uncertain",
    "unsure": "uncertain",
    "unworthy": "worthless",
    "up-and-coming": "energetic",
    "upset": "confused",
    "use_up": "exhausted",
    "vex": "annoyed",
    "vexed": "annoyed",
    "vigorous": "vigorous",
    "vile": "worthless",
    "virulent": "bitter",
    "vital": "lively",
    "vitriolic": "bitter",
    "warn": "discouraged",
    "wash_up": "exhausted",
    "washed-out": "worn-out",
    "wear": "fatigued",
    "wear_down": "fatigued",
    "wear_out": "fatigued",
    "wear_upon": "fatigued",
    "weary": "fatigued",
    "wild": "Angry",
    "wipe_out": "exhausted",
    "woeful": "miserable",
    "worn-out": "worn-out",
    "worn_out": "worn-out",
    "worthless": "worthless",
    "wretched": "miserable",
    "zippy": "lively"
}